determined/__init__.py
determined/_env_context.py
determined/_execution.py
determined/_experiment_config.py
determined/_import.py
determined/_info.py
determined/_trial.py
determined/_trial_context.py
determined/_trial_controller.py
determined/constants.py
determined/errors.py
determined/gpu.py
determined/horovod.py
determined/ipc.py
determined/load.py
determined/py.typed
determined/util.py
determined/workload.py
determined/cli/__init__.py
determined/cli/__main__.py
determined/cli/_declarative_argparse.py
determined/cli/_util.py
determined/cli/agent.py
determined/cli/checkpoint.py
determined/cli/cli.py
determined/cli/command.py
determined/cli/config_policies.py
determined/cli/dev.py
determined/cli/errors.py
determined/cli/experiment.py
determined/cli/job.py
determined/cli/master.py
determined/cli/model.py
determined/cli/notebook.py
determined/cli/ntsc.py
determined/cli/oauth.py
determined/cli/project.py
determined/cli/proxy.py
determined/cli/rbac.py
determined/cli/render.py
determined/cli/resource_pool.py
determined/cli/resources.py
determined/cli/shell.py
determined/cli/sso.py
determined/cli/task.py
determined/cli/template.py
determined/cli/tensorboard.py
determined/cli/token.py
determined/cli/top_arg_descriptions.py
determined/cli/trial.py
determined/cli/tunnel.py
determined/cli/user.py
determined/cli/user_groups.py
determined/cli/version.py
determined/cli/workspace.py
determined/common/__init__.py
determined/common/_logging.py
determined/common/check.py
determined/common/constants.py
determined/common/context.py
determined/common/detignore.py
determined/common/detlomond.py
determined/common/py.typed
determined/common/util.py
determined/common/v1file_utils.py
determined/common/api/__init__.py
determined/common/api/_rbac.py
determined/common/api/_session.py
determined/common/api/_util.py
determined/common/api/analytics.py
determined/common/api/authentication.py
determined/common/api/bindings.py
determined/common/api/certs.py
determined/common/api/errors.py
determined-0.38.1.dist-info/METADATA
determined-0.38.1.dist-info/WHEEL
determined-0.38.1.dist-info/entry_points.txt
determined-0.38.1.dist-info/top_level.txt
determined-0.38.1.dist-info/RECORD
