Metadata-Version: 2.1
Name: determined
Version: 0.38.1
Summary: Determined AI: The fastest and easiest way to build deep learning models.
Author-email: Determined AI <ai-open-source@hpe.com>
Project-URL: Homepage, https://determined.ai/
Project-URL: Documentation, https://docs.determined.ai/
Classifier: License :: OSI Approved :: Apache Software License
Requires-Python: >=3.8
Requires-Dist: matplotlib
Requires-Dist: packaging
Requires-Dist: numpy>=1.16.2
Requires-Dist: psutil
Requires-Dist: pyzmq>=18.1.0
Requires-Dist: certifi
Requires-Dist: filelock
Requires-Dist: requests<2.32.0
Requires-Dist: google-cloud-storage
Requires-Dist: lomond>=0.3.3
Requires-Dist: pathspec>=0.6.0
Requires-Dist: azure-core
Requires-Dist: azure-storage-blob
Requires-Dist: termcolor>=1.1.0
Requires-Dist: boto3
Requires-Dist: argcomplete>=1.9.4
Requires-Dist: gitpython>=3.1.3
Requires-Dist: pyOpenSSL>=19.1.0
Requires-Dist: python-dateutil
Requires-Dist: pytz
Requires-Dist: tabulate>=0.8.3
Requires-Dist: ruamel.yaml
Requires-Dist: docker[ssh]>=3.7.3
Requires-Dist: google-api-python-client>=1.12.1
Requires-Dist: paramiko>=2.4.2
Requires-Dist: tqdm
Requires-Dist: appdirs
Requires-Dist: analytics-python
Requires-Dist: oschmod; platform_system == "Windows"
